{
  "status": 0,
  "result": [
    {
      "createdById": "0054x0000011h5zAAA",
      "createdByName": "Christopher Spencer",
      "createdDate": "2020-11-09T13:28:49.000Z",
      "fileName": "classes/ltngsharing__TestLightningSharing.cls",
      "fullName": "ltngsharing__TestLightningSharing",
      "id": "01p4x000000Yu0QAAS",
      "lastModifiedById": "0054x0000011h5zAAA",
      "lastModifiedByName": "Christopher Spencer",
      "lastModifiedDate": "2020-11-09T13:28:49.000Z",
      "manageableState": "installed",
      "namespacePrefix": "ltngsharing",
      "type": "ApexClass"
    },
    {
      "createdById": "0054x0000011h5zAAA",
      "createdByName": "Christopher Spencer",
      "createdDate": "2020-11-23T02:18:07.000Z",
      "fileName": "classes/ContactTriggerHandlerTest.cls",
      "fullName": "ContactTriggerHandlerTest",
      "id": "01p4x000003HZEuAAO",
      "lastModifiedById": "0054x0000011h5zAAA",
      "lastModifiedByName": "Christopher Spencer",
      "lastModifiedDate": "2020-11-23T02:32:01.000Z",
      "manageableState": "unmanaged",
      "type": "ApexClass"
    },
    {
      "createdById": "0054x0000011h5zAAA",
      "createdByName": "Christopher Spencer",
      "createdDate": "2020-11-04T19:52:08.000Z",
      "fileName": "classes/trlhdtips__tt_UtilControllerTest.cls",
      "fullName": "trlhdtips__tt_UtilControllerTest",
      "id": "01p4x0000008YtQAAU",
      "lastModifiedById": "0054x0000011h5zAAA",
      "lastModifiedByName": "Christopher Spencer",
      "lastModifiedDate": "2020-11-04T19:52:08.000Z",
      "manageableState": "installed",
      "namespacePrefix": "trlhdtips",
      "type": "ApexClass"
    },
    {
      "createdById": "0054x0000011h5zAAA",
      "createdByName": "Christopher Spencer",
      "createdDate": "2020-11-23T00:05:17.000Z",
      "fileName": "classes/ContactTriggerHandler.cls",
      "fullName": "ContactTriggerHandler",
      "id": "01p4x000003HY1nAAG",
      "lastModifiedById": "0054x0000011h5zAAA",
      "lastModifiedByName": "Christopher Spencer",
      "lastModifiedDate": "2020-11-23T04:01:16.000Z",
      "manageableState": "unmanaged",
      "type": "ApexClass"
    },
    {
      "createdById": "0054x0000011h5zAAA",
      "createdByName": "Christopher Spencer",
      "createdDate": "2020-11-09T13:28:48.000Z",
      "fileName": "classes/ltngsharing__LightningSharing.cls",
      "fullName": "ltngsharing__LightningSharing",
      "id": "01p4x000000Yu0PAAS",
      "lastModifiedById": "0054x0000011h5zAAA",
      "lastModifiedByName": "Christopher Spencer",
      "lastModifiedDate": "2020-11-09T13:28:48.000Z",
      "manageableState": "installed",
      "namespacePrefix": "ltngsharing",
      "type": "ApexClass"
    },
    {
      "createdById": "0054x0000011h5zAAA",
      "createdByName": "Christopher Spencer",
      "createdDate": "2020-11-15T21:35:03.000Z",
      "fileName": "classes/FibonacciTest.cls",
      "fullName": "FibonacciTest",
      "id": "01p4x000000bJFyAAM",
      "lastModifiedById": "0054x0000011h5zAAA",
      "lastModifiedByName": "Christopher Spencer",
      "lastModifiedDate": "2020-11-15T21:51:16.000Z",
      "manageableState": "unmanaged",
      "type": "ApexClass"
    },
    {
      "createdById": "0054x0000011h5zAAA",
      "createdByName": "Christopher Spencer",
      "createdDate": "2020-11-13T21:27:07.000Z",
      "fileName": "classes/P0B.cls",
      "fullName": "P0B",
      "id": "01p4x000000aziCAAQ",
      "lastModifiedById": "0054x0000011h5zAAA",
      "lastModifiedByName": "Christopher Spencer",
      "lastModifiedDate": "2020-11-23T19:34:15.000Z",
      "manageableState": "unmanaged",
      "type": "ApexClass"
    },
    {
      "createdById": "0054x0000011h5zAAA",
      "createdByName": "Christopher Spencer",
      "createdDate": "2020-11-15T21:04:42.000Z",
      "fileName": "classes/P0BTesting.cls",
      "fullName": "P0BTesting",
      "id": "01p4x000000bIzNAAU",
      "lastModifiedById": "0054x0000011h5zAAA",
      "lastModifiedByName": "Christopher Spencer",
      "lastModifiedDate": "2020-11-15T21:04:42.000Z",
      "manageableState": "unmanaged",
      "type": "ApexClass"
    },
    {
      "createdById": "0054x0000011h5zAAA",
      "createdByName": "Christopher Spencer",
      "createdDate": "2020-11-04T19:52:08.000Z",
      "fileName": "classes/trlhdtips__tt_UtilController.cls",
      "fullName": "trlhdtips__tt_UtilController",
      "id": "01p4x0000008YtPAAU",
      "lastModifiedById": "0054x0000011h5zAAA",
      "lastModifiedByName": "Christopher Spencer",
      "lastModifiedDate": "2020-11-04T19:52:08.000Z",
      "manageableState": "installed",
      "namespacePrefix": "trlhdtips",
      "type": "ApexClass"
    },
    {
      "createdById": "0054x0000011h5zAAA",
      "createdByName": "Christopher Spencer",
      "createdDate": "2020-11-15T21:36:00.000Z",
      "fileName": "classes/Fibonacci.cls",
      "fullName": "Fibonacci",
      "id": "01p4x000000bJG3AAM",
      "lastModifiedById": "0054x0000011h5zAAA",
      "lastModifiedByName": "Christopher Spencer",
      "lastModifiedDate": "2020-11-16T10:25:56.000Z",
      "manageableState": "unmanaged",
      "type": "ApexClass"
    }
  ]
}
