{
  "status": 0,
  "result": [
    {
      "createdById": "0054x0000011h5zAAA",
      "createdByName": "Christopher Spencer",
      "createdDate": "2020-11-04T19:52:08.000Z",
      "fileName": "flows/net_promoter_score.flow",
      "fullName": "net_promoter_score",
      "id": "3014x00000000kTAAQ",
      "lastModifiedById": "0054x0000011h5zAAA",
      "lastModifiedByName": "Christopher Spencer",
      "lastModifiedDate": "2020-11-04T19:52:08.000Z",
      "manageableState": "unmanaged",
      "type": "Flow"
    },
    {
      "createdById": "0054x0000011h5zAAA",
      "createdByName": "Christopher Spencer",
      "createdDate": "2020-11-04T19:52:08.000Z",
      "fileName": "flows/customer_satisfaction.flow",
      "fullName": "customer_satisfaction",
      "id": "3014x00000000kUAAQ",
      "lastModifiedById": "0054x0000011h5zAAA",
      "lastModifiedByName": "Christopher Spencer",
      "lastModifiedDate": "2020-11-04T19:52:08.000Z",
      "manageableState": "unmanaged",
      "type": "Flow"
    },
    {
      "createdById": "0054x0000011h5zAAA",
      "createdByName": "Christopher Spencer",
      "createdDate": "2020-11-22T23:52:54.000Z",
      "fileName": "flows/New_Contact_with_no_account.flow",
      "fullName": "New_Contact_with_no_account",
      "id": "3014x000000TSlOAAW",
      "lastModifiedById": "0054x0000011h5zAAA",
      "lastModifiedByName": "Christopher Spencer",
      "lastModifiedDate": "2020-11-22T23:53:00.000Z",
      "manageableState": "unmanaged",
      "type": "Flow"
    },
    {
      "createdById": "0054x0000011h5zAAA",
      "createdByName": "Christopher Spencer",
      "createdDate": "2020-11-22T23:50:42.000Z",
      "fileName": "flows/Create_new_Contact.flow",
      "fullName": "Create_new_Contact",
      "id": "3014x000000TSlMAAW",
      "lastModifiedById": "0054x0000011h5zAAA",
      "lastModifiedByName": "Christopher Spencer",
      "lastModifiedDate": "2020-11-22T23:50:56.000Z",
      "manageableState": "unmanaged",
      "type": "Flow"
    }
  ]
}
